pseudoservice/__init__.py
pseudoservice/main.py
pseudoservice-0.1.0.dist-info/METADATA
pseudoservice-0.1.0.dist-info/WHEEL
pseudoservice-0.1.0.dist-info/top_level.txt
pseudoservice-0.1.0.dist-info/RECORD
