Metadata-Version: 2.1
Name: pseudoservice
Version: 0.1.0
Summary: A simple threaded task launcher that emulates unix service-unit style behavior
Home-page: https://github.com/manbehindthemadness/pseudoservice
Author: Manbehindthemadness
Author-email: manbehindthemadness@gmail.com
Classifier: Programming Language :: Python :: 3
Classifier: License :: OSI Approved :: MIT License
Classifier: Operating System :: OS Independent
Requires-Python: >=3.6
